<annotation><folder>data/MyDataset/JSON/fimg_2072.json</folder><filename>data/MyDataset/JSON/fimg_2072.json</filename><path>/home/aistudio\data/MyDataset/JSON/fimg_2072.json</path><source><database>Unknown</database></source><size><width>500</width><height>396</height><depth>3</depth></size><segmented>0</segmented><object><name> &#21487;&#22238;&#25910;&#29289;/&#22609;&#26009;&#29609;&#20855;</name><pose>Unspecified</pose><truncated>0</truncated><difficult>0</difficult><bndbox><xmin>314</xmin><ymin>190</ymin><xmax>450</xmax><ymax>320</ymax></bndbox></object><object><name> &#21487;&#22238;&#25910;&#29289;/&#22609;&#26009;&#29609;&#20855;</name><pose>Unspecified</pose><truncated>0</truncated><difficult>0</difficult><bndbox><xmin>105</xmin><ymin>283</ymin><xmax>250</xmax><ymax>383</ymax></bndbox></object><object><name> &#21487;&#22238;&#25910;&#29289;/&#22609;&#26009;&#29609;&#20855;</name><pose>Unspecified</pose><truncated>0</truncated><difficult>0</difficult><bndbox><xmin>267</xmin><ymin>64</ymin><xmax>374</xmax><ymax>176</ymax></bndbox></object></annotation>