<annotation><folder>data/MyDataset/JSON/fimg_64.json</folder><filename>data/MyDataset/JSON/fimg_64.json</filename><path>/home/aistudio\data/MyDataset/JSON/fimg_64.json</path><source><database>Unknown</database></source><size><width>300</width><height>300</height><depth>3</depth></size><segmented>0</segmented><object><name>&#20854;&#20182;&#22403;&#22334;/&#19968;&#27425;&#24615;&#24555;&#39184;&#30418;</name><pose>Unspecified</pose><truncated>0</truncated><difficult>0</difficult><bndbox><xmin>14</xmin><ymin>25</ymin><xmax>282</xmax><ymax>273</ymax></bndbox></object></annotation>