<annotation><folder>data/MyDataset/JSON/fimg_423.json</folder><filename>data/MyDataset/JSON/fimg_423.json</filename><path>/home/aistudio\data/MyDataset/JSON/fimg_423.json</path><source><database>Unknown</database></source><size><width>434</width><height>434</height><depth>3</depth></size><segmented>0</segmented><object><name> &#20854;&#20182;&#22403;&#22334;/&#28895;&#33922;</name><pose>Unspecified</pose><truncated>0</truncated><difficult>0</difficult><bndbox><xmin>38</xmin><ymin>121</ymin><xmax>101</xmax><ymax>388</ymax></bndbox></object><object><name> &#20854;&#20182;&#22403;&#22334;/&#28895;&#33922;</name><pose>Unspecified</pose><truncated>0</truncated><difficult>0</difficult><bndbox><xmin>211</xmin><ymin>145</ymin><xmax>269</xmax><ymax>395</ymax></bndbox></object><object><name> &#20854;&#20182;&#22403;&#22334;/&#28895;&#33922;</name><pose>Unspecified</pose><truncated>0</truncated><difficult>0</difficult><bndbox><xmin>335</xmin><ymin>201</ymin><xmax>378</xmax><ymax>403</ymax></bndbox></object></annotation>