<annotation><folder>data/MyDataset/JSON/fimg_1265.json</folder><filename>data/MyDataset/JSON/fimg_1265.json</filename><path>/home/aistudio\data/MyDataset/JSON/fimg_1265.json</path><source><database>Unknown</database></source><size><width>428</width><height>428</height><depth>3</depth></size><segmented>0</segmented><object><name> &#21416;&#20313;&#22403;&#22334;/&#34507;&#22771;</name><pose>Unspecified</pose><truncated>0</truncated><difficult>0</difficult><bndbox><xmin>38</xmin><ymin>132</ymin><xmax>154</xmax><ymax>280</ymax></bndbox></object><object><name> &#21416;&#20313;&#22403;&#22334;/&#34507;&#22771;</name><pose>Unspecified</pose><truncated>0</truncated><difficult>0</difficult><bndbox><xmin>167</xmin><ymin>200</ymin><xmax>290</xmax><ymax>349</ymax></bndbox></object><object><name> &#21416;&#20313;&#22403;&#22334;/&#34507;&#22771;</name><pose>Unspecified</pose><truncated>0</truncated><difficult>0</difficult><bndbox><xmin>298</xmin><ymin>149</ymin><xmax>407</xmax><ymax>298</ymax></bndbox></object></annotation>