<annotation><folder>data/MyDataset/JSON/fimg_371.json</folder><filename>data/MyDataset/JSON/fimg_371.json</filename><path>/home/aistudio\data/MyDataset/JSON/fimg_371.json</path><source><database>Unknown</database></source><size><width>400</width><height>400</height><depth>3</depth></size><segmented>0</segmented><object><name> &#20854;&#20182;&#22403;&#22334;/&#28895;&#33922;</name><pose>Unspecified</pose><truncated>0</truncated><difficult>0</difficult><bndbox><xmin>113</xmin><ymin>110</ymin><xmax>197</xmax><ymax>186</ymax></bndbox></object><object><name> &#20854;&#20182;&#22403;&#22334;/&#28895;&#33922;</name><pose>Unspecified</pose><truncated>0</truncated><difficult>0</difficult><bndbox><xmin>232</xmin><ymin>264</ymin><xmax>285</xmax><ymax>358</ymax></bndbox></object><object><name> &#20854;&#20182;&#22403;&#22334;/&#28895;&#33922;</name><pose>Unspecified</pose><truncated>0</truncated><difficult>0</difficult><bndbox><xmin>296</xmin><ymin>126</ymin><xmax>357</xmax><ymax>230</ymax></bndbox></object></annotation>