<annotation><folder>data/MyDataset/JSON/fimg_910.json</folder><filename>data/MyDataset/JSON/fimg_910.json</filename><path>/home/aistudio\data/MyDataset/JSON/fimg_910.json</path><source><database>Unknown</database></source><size><width>360</width><height>360</height><depth>3</depth></size><segmented>0</segmented><object><name> &#21416;&#20313;&#22403;&#22334;/&#27700;&#26524;&#26524;&#30382;</name><pose>Unspecified</pose><truncated>0</truncated><difficult>0</difficult><bndbox><xmin>0</xmin><ymin>46</ymin><xmax>357</xmax><ymax>319</ymax></bndbox></object></annotation>