<annotation><folder>data/MyDataset/JSON/fimg_964.json</folder><filename>data/MyDataset/JSON/fimg_964.json</filename><path>/home/aistudio\data/MyDataset/JSON/fimg_964.json</path><source><database>Unknown</database></source><size><width>289</width><height>175</height><depth>3</depth></size><segmented>0</segmented><object><name> &#21416;&#20313;&#22403;&#22334;/&#27700;&#26524;&#26524;&#30382;</name><pose>Unspecified</pose><truncated>0</truncated><difficult>0</difficult><bndbox><xmin>51</xmin><ymin>33</ymin><xmax>285</xmax><ymax>110</ymax></bndbox></object></annotation>